MANIFEST.in
README.txt
requirements.txt
setup.py
test_requirements.txt
version.txt
cloudshell/__init__.py
cloudshell/power/__init__.py
cloudshell/power/pdu/__init__.py
cloudshell/power/pdu/power_resource_driver_interface.py
cloudshell/power/pdu/device/__init__.py
cloudshell/power/pdu/device/outlet.py
cloudshell/power/pdu/device/pdu_factory.py
cloudshell/power/pdu/managed_devices/__init__.py
cloudshell/power/pdu/managed_devices/connected_to_pdu_resource.py
cloudshell_pdu_core.egg-info/PKG-INFO
cloudshell_pdu_core.egg-info/SOURCES.txt
cloudshell_pdu_core.egg-info/dependency_links.txt
cloudshell_pdu_core.egg-info/requires.txt
cloudshell_pdu_core.egg-info/top_level.txt