Metadata-Version: 1.0
Name: cloudshell-pdu-core
Version: 1.0.21
Summary: QualiSystems PDU core package
Home-page: http://www.qualisystems.com/
Author: QualiSystems
Author-email: info@qualisystems.com
License: UNKNOWN
Platform: UNKNOWN
